duckops/__init__.py
duckops/_sqla_patch.py
duckops/_types.py
duckops/agg.py
duckops/all.py
duckops/blob.py
duckops/dt.py
duckops/helpers.py
duckops/json.py
duckops/nested.py
duckops/num.py
duckops/str.py
duckops/syntax.py
duckops/unknown.py
duckops/util.py
duckops/win.py
duckops/_functions/agg.py
duckops/_functions/blob.py
duckops/_functions/dt.py
duckops/_functions/json.py
duckops/_functions/nested.py
duckops/_functions/num.py
duckops/_functions/str.py
duckops/_functions/unknown.py
duckops/_functions/util.py
duckops/core/_databackends.py
duckops/core/convert.py
duckops/core/data_style.py
duckops/core/dispatch.py
duckops/core/query_call.py
duckops/core/siuba.py
duckops/core/sql.py
duckops/tests/test_core_dispatch.py
duckops/tests/test_core_siuba.py
duckops/tests/test_data.py
duckops-0.1.0.dist-info/METADATA
duckops-0.1.0.dist-info/WHEEL
duckops-0.1.0.dist-info/top_level.txt
duckops-0.1.0.dist-info/RECORD
